chickadee/Component.py
chickadee/Dispatcher.py
chickadee/GekkoDispatch.py
chickadee/MPC.py
chickadee/PyOptSparseDispatch.py
chickadee/Resource.py
chickadee/Solution.py
chickadee/TimeSeries.py
chickadee/__init__.py
chickadee_opt-0.1.1.dist-info/LICENSE
chickadee_opt-0.1.1.dist-info/METADATA
chickadee_opt-0.1.1.dist-info/WHEEL
chickadee_opt-0.1.1.dist-info/top_level.txt
chickadee_opt-0.1.1.dist-info/RECORD
