Metadata-Version: 2.1
Name: chickadee-opt
Version: 0.1.1
Summary: A tool for advanced dispatch optimization of hybrid energy systems
Home-page: https://github.com/dhill2522/chickadee
Author: Daniel Hill
Author-email: dhill2522@gmail.com
License: MIT
Platform: UNKNOWN
Requires-Python: >=3.5
